{
  "annotations": {
    "list": [
      {
        "builtIn": 1,
        "datasource": {
          "type": "grafana",
          "uid": "-- Grafana --"
        },
        "enable": true,
        "hide": true,
        "iconColor": "rgba(0, 211, 255, 1)",
        "name": "Annotations & Alerts",
        "target": {
          "limit": 100,
          "matchAny": false,
          "tags": [],
          "type": "dashboard"
        },
        "type": "dashboard"
      }
    ]
  },
  "editable": true,
  "fiscalYearStartMonth": 0,
  "graphTooltip": 0,
  "links": [],
  "liveNow": false,
  "panels": [
    {
      "datasource": {
        "type": "influxdb",
        "uid": "P951FEA4DE68E13C5"
      },
      "fieldConfig": {
        "defaults": {
          "color": {
            "mode": "palette-classic"
          },
          "custom": {
            "axisLabel": "",
            "axisPlacement": "auto",
            "barAlignment": 0,
            "drawStyle": "line",
            "fillOpacity": 10,
            "gradientMode": "none",
            "hideFrom": {
              "legend": false,
              "tooltip": false,
              "viz": false
            },
            "lineInterpolation": "linear",
            "lineWidth": 1,
            "pointSize": 5,
            "scaleDistribution": {
              "type": "linear"
            },
            "showPoints": "auto",
            "spanNulls": true,
            "stacking": {
              "group": "A",
              "mode": "none"
            },
            "thresholdsStyle": {
              "mode": "off"
            }
          },
          "mappings": [],
          "thresholds": {
            "mode": "absolute",
            "steps": [
              {
                "color": "green",
                "value": null
              },
              {
                "color": "red",
                "value": 80
              }
            ]
          }
        },
        "overrides": []
      },
      "gridPos": {
        "h": 13,
        "w": 24,
        "x": 0,
        "y": 0
      },
      "id": 4,
      "options": {
        "legend": {
          "calcs": [],
          "displayMode": "list",
          "placement": "bottom"
        },
        "tooltip": {
          "mode": "single",
          "sort": "none"
        }
      },
      "targets": [
        {
          "datasource": {
            "type": "influxdb",
            "uid": "P951FEA4DE68E13C5"
          },
          "query": "from(bucket: \"env-studio\")\n  |> range(start: v.timeRangeStart, stop: v.timeRangeStop)\n  |> filter(fn: (r) => r[\"_measurement\"] == \"StateExecutionMeasure\" and\n                       r[\"_field\"] == \"timeTakeMilliseconds\")\n  |> group(columns: [\"state\"])\n  |> aggregateWindow(every: 1s, fn: sum, createEmpty: false)\n  |> drop(columns: [\"_start\", \"_stop\", \"finalStatus\", \"jobId\", \"size\", \"namespace\", \"typeJob\"])",
          "refId": "A"
        }
      ],
      "title": "Number of Jobs per State",
      "type": "timeseries"
    },
    {
      "datasource": {
        "type": "influxdb",
        "uid": "P951FEA4DE68E13C5"
      },
      "fieldConfig": {
        "defaults": {
          "color": {
            "mode": "palette-classic"
          },
          "custom": {
            "axisLabel": "",
            "axisPlacement": "auto",
            "axisSoftMin": 0,
            "fillOpacity": 80,
            "gradientMode": "none",
            "hideFrom": {
              "legend": false,
              "tooltip": false,
              "viz": false
            },
            "lineWidth": 1,
            "scaleDistribution": {
              "type": "linear"
            }
          },
          "mappings": [],
          "thresholds": {
            "mode": "absolute",
            "steps": [
              {
                "color": "green",
                "value": null
              },
              {
                "color": "red",
                "value": 80
              }
            ]
          },
          "unit": "ms"
        },
        "overrides": []
      },
      "gridPos": {
        "h": 16,
        "w": 24,
        "x": 0,
        "y": 0
      },
      "id": 2,
      "options": {
        "barRadius": 0,
        "barWidth": 0.97,
        "groupWidth": 0.7,
        "legend": {
          "calcs": [
            "sum",
            "mean",
            "max",
            "min"
          ],
          "displayMode": "table",
          "placement": "bottom"
        },
        "orientation": "auto",
        "showValue": "auto",
        "stacking": "normal",
        "tooltip": {
          "mode": "single",
          "sort": "none"
        },
        "xField": "_time",
        "xTickLabelRotation": 0,
        "xTickLabelSpacing": 200
      },
      "targets": [
        {
          "datasource": {
            "type": "influxdb",
            "uid": "P951FEA4DE68E13C5"
          },
          "query": "from(bucket: \"env-studio\")\n  |> range(start: v.timeRangeStart, stop: v.timeRangeStop)\n  |> filter(fn: (r) => r[\"_measurement\"] == \"TotalTimeExecutionMeasure\" and\n                       r[\"_field\"] == \"timeTakeMilliseconds\")\n  |> group(columns: [\"state\"])\n  |> truncateTimeColumn(unit: 1d)\n  |> drop(columns: [\"_start\", \"_stop\", \"finalStatus\", \"jobId\", \"size\", \"namespace\", \"typeJob\"])",
          "refId": "A"
        }
      ],
      "title": "Time grouped by state and day",
      "type": "barchart"
    }
  ],
  "refresh": "",
  "schemaVersion": 36,
  "style": "dark",
  "tags": [],
  "templating": {
    "list": []
  },
  "time": {
    "from": "2021-06-19T22:00:00.000Z",
    "to": "now"
  },
  "timepicker": {},
  "timezone": "",
  "title": "Job State",
  "uid": "7t55FLQnk",
  "version": 1,
  "weekStart": ""
}